.gitignore
MANIFEST.in
README.rst
setup.cfg
setup.py
docs/HISTORY.txt
raptus/__init__.py
raptus.multilanguageurls.egg-info/PKG-INFO
raptus.multilanguageurls.egg-info/SOURCES.txt
raptus.multilanguageurls.egg-info/dependency_links.txt
raptus.multilanguageurls.egg-info/entry_points.txt
raptus.multilanguageurls.egg-info/namespace_packages.txt
raptus.multilanguageurls.egg-info/not-zip-safe
raptus.multilanguageurls.egg-info/requires.txt
raptus.multilanguageurls.egg-info/top_level.txt
raptus/multilanguageurls/__init__.py
raptus/multilanguageurls/configure.zcml
raptus/multilanguageurls/handler.py
raptus/multilanguageurls/interfaces.py
raptus/multilanguageurls/patches.py
raptus/multilanguageurls/rename.py
raptus/multilanguageurls/traverser.py
raptus/multilanguageurls/update.py
raptus/multilanguageurls/profiles/default/actions.xml
raptus/multilanguageurls/profiles/default/metadata.xml
raptus/multilanguageurls/profiles/default/skins.xml
raptus/multilanguageurls/profiles/default/tinymce.xml
raptus/multilanguageurls/skins/raptus_multilanguageurls/folder_rename_form.py