Metadata-Version: 1.1
Name: raptus.multilanguageurls
Version: 1.0a9
Summary: Provides multilanguage URLs for Plone sites using raptus.multilanguagefields
Home-page: https://github.com/Raptus/raptus.multilanguageurls
Author: Raptus AG
Author-email: dev@raptus.com
License: GPL
Platform: UNKNOWN
Classifier: Programming Language :: Python
Classifier: Topic :: Software Development :: Libraries :: Python Modules
